commonutility/__init__.py
commonutility-0.0.15.dist-info/LICENCE.txt
commonutility-0.0.15.dist-info/METADATA
commonutility-0.0.15.dist-info/WHEEL
commonutility-0.0.15.dist-info/top_level.txt
commonutility-0.0.15.dist-info/RECORD
